{
  "orari": "Siamo aperti dal lunedì al venerdì, dalle 9:00 alle 18:00. Sabato e domenica chiusi.",
  "contatti": "Puoi contattarci via email a info@esempio.it oppure al telefono 123-456-789",
  "servizi": "Offriamo servizi di consulenza, supporto tecnico e formazione personalizzata",
  "prezzi": "I nostri prezzi variano in base al servizio richiesto. Contattaci per un preventivo gratuito.",
  "pagamenti": "Accettiamo pagamenti tramite bonifico bancario, carta di credito e PayPal",
  "assistenza": "Il nostro servizio di assistenza è disponibile via email e telefono durante gli orari di apertura",
  "spedizioni": "Le spedizioni vengono effettuate entro 24-48 ore lavorative dall'ordine",
  "resi": "È possibile effettuare resi entro 14 giorni dall'acquisto, con prodotto integro e nella confezione originale"
}